olla_cli/__init__.py
olla_cli/cli.py
olla_cli/cli/__init__.py
olla_cli/cli/code_commands.py
olla_cli/cli/config_commands.py
olla_cli/cli/main.py
olla_cli/cli/model_commands.py
olla_cli/cli/task_commands.py
olla_cli/client/__init__.py
olla_cli/client/model_manager.py
olla_cli/client/ollama_client.py
olla_cli/commands/__init__.py
olla_cli/commands/implementations.py
olla_cli/config/__init__.py
olla_cli/config/config.py
olla_cli/config/logging_config.py
olla_cli/context/__init__.py
olla_cli/context/context_builder.py
olla_cli/context/context_cli.py
olla_cli/context/context_manager.py
olla_cli/context/dependency_graph.py
olla_cli/core/__init__.py
olla_cli/core/exceptions.py
olla_cli/task/__init__.py
olla_cli/task/discovery.py
olla_cli/task/executor.py
olla_cli/task/history.py
olla_cli/task/models.py
olla_cli/task/parser.py
olla_cli/ui/__init__.py
olla_cli/ui/formatter_factory.py
olla_cli/ui/interactive_repl.py
olla_cli/ui/interactive_session.py
olla_cli/ui/output_formatter.py
olla_cli/utils/__init__.py
olla_cli/utils/formatters.py
olla_cli/utils/helpers.py
olla_cli/utils/messages.py
olla_cli/utils/parsers.py
olla_cli-0.3.0.dist-info/licenses/LICENSE
olla_cli-0.3.0.dist-info/METADATA
olla_cli-0.3.0.dist-info/WHEEL
olla_cli-0.3.0.dist-info/entry_points.txt
olla_cli-0.3.0.dist-info/top_level.txt
olla_cli-0.3.0.dist-info/RECORD
