Metadata-Version: 2.4
Name: olla-cli
Version: 0.3.0
Summary: Your AI-Powered Coding Assistant in the Terminal
Author-email: Mahinuzzaman <mahinuzzaman@example.com>
License: MIT
Project-URL: Bug Tracker, https://github.com/mahinuzzaman/ollama-cli/issues
Project-URL: Source Code, https://github.com/mahinuzzaman/ollama-cli
Classifier: Development Status :: 3 - Alpha
Classifier: Intended Audience :: Developers
Classifier: Topic :: Software Development :: Code Generators
Classifier: Topic :: Scientific/Engineering :: Artificial Intelligence
Classifier: License :: OSI Approved :: MIT License
Classifier: Operating System :: OS Independent
Classifier: Programming Language :: Python :: 3
Classifier: Programming Language :: Python :: 3.8
Classifier: Programming Language :: Python :: 3.9
Classifier: Programming Language :: Python :: 3.10
Classifier: Programming Language :: Python :: 3.11
Classifier: Programming Language :: Python :: 3.12
Requires-Python: >=3.8
License-File: LICENSE
Requires-Dist: click>=8.0.0
Requires-Dist: pyyaml>=6.0
Requires-Dist: ollama>=0.2.0
Requires-Dist: aiohttp>=3.8.0
Requires-Dist: prompt_toolkit>=3.0.0
Requires-Dist: pygments>=2.0.0
Requires-Dist: rich>=13.0.0
Requires-Dist: pyperclip>=1.8.0
Requires-Dist: markdown>=3.4.0
Provides-Extra: dev
Requires-Dist: pytest>=6.0; extra == "dev"
Requires-Dist: pytest-cov>=3.0; extra == "dev"
Requires-Dist: pytest-mock>=3.6; extra == "dev"
Requires-Dist: flake8>=3.9; extra == "dev"
Requires-Dist: black>=22.0; extra == "dev"
Requires-Dist: isort>=5.0; extra == "dev"
Requires-Dist: mypy>=0.900; extra == "dev"
Requires-Dist: tox>=3.20; extra == "dev"
Requires-Dist: ruff>=0.1.0; extra == "dev"
Dynamic: license-file
